taurex/__init__.py
taurex/_citation.py
taurex/_version.py
taurex/binning/__init__.py
taurex/binning/binner.py
taurex/binning/fluxbinner.py
taurex/binning/lightcurvebinner.py
taurex/binning/nativebinner.py
taurex/binning/simplebinner.py
taurex/cache/__init__.py
taurex/cache/ciaacache.py
taurex/cache/globalcache.py
taurex/cache/ktablecache.py
taurex/cache/opacitycache.py
taurex/cache/singleton.py
taurex/chemistry.py
taurex/cia/__init__.py
taurex/cia/cia.py
taurex/cia/hitrancia.py
taurex/cia/picklecia.py
taurex/constants.py
taurex/contributions/__init__.py
taurex/contributions/absorption.py
taurex/contributions/cia.py
taurex/contributions/contribution.py
taurex/contributions/flatmie.py
taurex/contributions/hm.py
taurex/contributions/leemie.py
taurex/contributions/rayleigh.py
taurex/contributions/simpleclouds.py
taurex/core/__init__.py
taurex/core/priors.py
taurex/data/__init__.py
taurex/data/citation.py
taurex/data/fittable.py
taurex/data/planet.py
taurex/data/profiles/__init__.py
taurex/data/profiles/chemistry/__init__.py
taurex/data/profiles/chemistry/autochemistry.py
taurex/data/profiles/chemistry/chemistry.py
taurex/data/profiles/chemistry/filechemistry.py
taurex/data/profiles/chemistry/gas/__init__.py
taurex/data/profiles/chemistry/gas/arraygas.py
taurex/data/profiles/chemistry/gas/constantgas.py
taurex/data/profiles/chemistry/gas/customgas.py
taurex/data/profiles/chemistry/gas/gas.py
taurex/data/profiles/chemistry/gas/powergas.py
taurex/data/profiles/chemistry/gas/twolayergas.py
taurex/data/profiles/chemistry/gas/twopointgas.py
taurex/data/profiles/chemistry/taurexchemistry.py
taurex/data/profiles/pressure/__init__.py
taurex/data/profiles/pressure/arraypressure.py
taurex/data/profiles/pressure/filepressure.py
taurex/data/profiles/pressure/pressureprofile.py
taurex/data/profiles/temperature/__init__.py
taurex/data/profiles/temperature/file.py
taurex/data/profiles/temperature/guillot.py
taurex/data/profiles/temperature/isothermal.py
taurex-3.3.2.dist-info/METADATA
taurex-3.3.2.dist-info/WHEEL
taurex-3.3.2.dist-info/entry_points.txt
taurex-3.3.2.dist-info/licenses/LICENSE
taurex-3.3.2.dist-info/RECORD
