Metadata-Version: 2.4
Name: taurex
Version: 3.3.2
Summary: TauREx3
License: BSDv3
License-File: LICENSE
Author: Ahmed Faris Al-Refaie
Author-email: ahmed.al-refaie.12@ucl.ac.uk
Requires-Python: >=3.10,<4.0
Classifier: Development Status :: 4 - Beta
Classifier: Environment :: Console
Classifier: Intended Audience :: Developers
Classifier: Intended Audience :: Science/Research
Classifier: License :: OSI Approved :: BSD License
Classifier: License :: Other/Proprietary License
Classifier: Operating System :: Microsoft :: Windows
Classifier: Operating System :: OS Independent
Classifier: Operating System :: POSIX
Classifier: Operating System :: POSIX :: Linux
Classifier: Operating System :: Unix
Classifier: Programming Language :: Python
Classifier: Programming Language :: Python :: 3
Classifier: Programming Language :: Python :: 3.10
Classifier: Programming Language :: Python :: 3.11
Classifier: Programming Language :: Python :: 3.12
Classifier: Programming Language :: Python :: 3.13
Classifier: Programming Language :: Python :: 3.14
Classifier: Topic :: Scientific/Engineering
Classifier: Topic :: Software Development :: Libraries
Provides-Extra: biblio
Provides-Extra: multinest
Provides-Extra: numba
Requires-Dist: astropy (>=6.0.0)
Requires-Dist: click (>=8.0.1)
Requires-Dist: configobj (>=5.0.0,<6.0.0)
Requires-Dist: h5py (>=3.9.0,<4.0.0)
Requires-Dist: nestle (>=0.2.0,<0.3.0)
Requires-Dist: numba (>=0.60.0) ; extra == "numba"
Requires-Dist: numpy (>=2.0.2,<3.0.0)
Requires-Dist: pybtex (>=0.24.0,<0.25.0) ; extra == "biblio"
Requires-Dist: pymultinest (>=2.12,<3.0) ; extra == "multinest"
Requires-Dist: scipy (>=1.11.3)
Requires-Dist: tabulate (>=0.9.0,<0.10.0)
Project-URL: Changelog, https://github.com/ahmed-f-alrefaie/taurex3/releases
Project-URL: Documentation, https://taurex3.readthedocs.io
Project-URL: Homepage, https://github.com/ahmed-f-alrefaie/taurex3
Project-URL: Repository, https://github.com/ahmed-f-alrefaie/taurex3
